verlib/__init__.py
verlib/integrations/__init__.py
verlib/integrations/flask.py
verlib/jsonrpc.py
verlib/verlib.py
verlib/verliberr.py
pyverlib-0.1.2.dist-info/METADATA
pyverlib-0.1.2.dist-info/WHEEL
pyverlib-0.1.2.dist-info/LICENSE.txt
pyverlib-0.1.2.dist-info/RECORD
