Metadata-Version: 2.1
Name: pyverlib
Version: 0.1.2
Summary: library for building RPC APIs
License: LICENSE.txt
Keywords: API,library,RPC
Author: stackswithans
Author-email: stexor12@gmail.com
Requires-Python: >=3.10,<4.0
Classifier: Development Status :: 4 - Beta
Classifier: License :: Other/Proprietary License
Classifier: Programming Language :: Python
Classifier: Programming Language :: Python :: 3
Classifier: Programming Language :: Python :: 3.10
Classifier: Programming Language :: Python :: 3.11
Provides-Extra: django
Provides-Extra: flask
Requires-Dist: django (>=4.1.7,<5.0.0) ; extra == "django"
Requires-Dist: flask (>=2.2.3,<3.0.0) ; extra == "flask"
Requires-Dist: schema (>=0.7.5,<0.8.0)
Requires-Dist: typing-extensions (>=4.5.0,<5.0.0)
